[
 {
  "action": "Schedule Review",
  "allow_self_approval": 1,
  "allowed": "HR",
  "condition": "doc.review_date",
  "docstatus": 0,
  "doctype": "Workflow Transition",
  "modified": "2025-01-12 17:39:12.415526",
  "name": "c0m387pdb7",
  "next_state": "Review Scheduled",
  "parent": "Employee Performance Review Cycle",
  "parentfield": "transitions",
  "parenttype": "Workflow",
  "state": "Pending Review",
  "workflow_builder_id": null
 },
 {
  "action": "Record Feedback",
  "allow_self_approval": 1,
  "allowed": "HR",
  "condition": "doc.feedback",
  "docstatus": 0,
  "doctype": "Workflow Transition",
  "modified": "2025-01-12 17:39:12.415872",
  "name": "8d89qrpa6n",
  "next_state": "Feedback Provided",
  "parent": "Employee Performance Review Cycle",
  "parentfield": "transitions",
  "parenttype": "Workflow",
  "state": "Review Scheduled",
  "workflow_builder_id": null
 },
 {
  "action": "Submit for Review",
  "allow_self_approval": 1,
  "allowed": "HR",
  "condition": "doc.feedback and doc.review_date",
  "docstatus": 0,
  "doctype": "Workflow Transition",
  "modified": "2025-01-12 17:39:12.416207",
  "name": "ifqt0fcqta",
  "next_state": "Under Approval",
  "parent": "Employee Performance Review Cycle",
  "parentfield": "transitions",
  "parenttype": "Workflow",
  "state": "Feedback Provided",
  "workflow_builder_id": null
 },
 {
  "action": "Review Approved",
  "allow_self_approval": 1,
  "allowed": "Manager",
  "condition": null,
  "docstatus": 0,
  "doctype": "Workflow Transition",
  "modified": "2025-01-12 17:39:12.416567",
  "name": "9c406hu5g2",
  "next_state": "Review Approved",
  "parent": "Employee Performance Review Cycle",
  "parentfield": "transitions",
  "parenttype": "Workflow",
  "state": "Under Approval",
  "workflow_builder_id": null
 },
 {
  "action": "Review Rejected",
  "allow_self_approval": 1,
  "allowed": "Manager",
  "condition": null,
  "docstatus": 0,
  "doctype": "Workflow Transition",
  "modified": "2025-01-12 17:39:12.416858",
  "name": "fllov4l6sv",
  "next_state": "Review Rejected",
  "parent": "Employee Performance Review Cycle",
  "parentfield": "transitions",
  "parenttype": "Workflow",
  "state": "Under Approval",
  "workflow_builder_id": null
 },
 {
  "action": "Update Feedback",
  "allow_self_approval": 1,
  "allowed": "HR",
  "condition": null,
  "docstatus": 0,
  "doctype": "Workflow Transition",
  "modified": "2025-01-12 17:39:12.417117",
  "name": "n05a5u7be1",
  "next_state": "Feedback Provided",
  "parent": "Employee Performance Review Cycle",
  "parentfield": "transitions",
  "parenttype": "Workflow",
  "state": "Review Rejected",
  "workflow_builder_id": null
 }
]